{
  "name": "Powerball",
  "shortName": "powerball",
  "apiId": "d6yy-54nr",
  "analysisStartDate": "10/04/2015",
  "fieldNumMax": 69,
  "bonusBallMax": 26,
  "daysDrawn": [
    "mon",
    "wed",
    "sat"
  ],
  "lastDrawDate": "11/28/2022",
  "fieldNumsOverdue": {
    "numbers": [
      "12",
      "61",
      "49",
      "04",
      "38",
      "52",
      "05",
      "10",
      "21",
      "09",
      "65",
      "33",
      "03",
      "17",
      "68",
      "41",
      "43",
      "26",
      "27",
      "08",
      "23",
      "42",
      "18",
      "37",
      "55"
    ],
    "overdueAmt": [
      27,
      20,
      19,
      18,
      18,
      18,
      16,
      13,
      13,
      11,
      10,
      9,
      8,
      7,
      7,
      6,
      5,
      4,
      4,
      3,
      3,
      2,
      1,
      1,
      1
    ]
  },
  "fieldNumAnalysis": [
    {
      "number": "01",
      "lastHitDate": "11/23/2022",
      "hitFreq": 14,
      "totalHits": 56,
      "noHitCount": 2,
      "drawsOverdue": 0
    },
    {
      "number": "02",
      "lastHitDate": "11/23/2022",
      "hitFreq": 13,
      "totalHits": 58,
      "noHitCount": 2,
      "drawsOverdue": 0
    },
    {
      "number": "03",
      "lastHitDate": "10/10/2022",
      "hitFreq": 12,
      "totalHits": 65,
      "noHitCount": 20,
      "drawsOverdue": 8
    },
    {
      "number": "04",
      "lastHitDate": "09/05/2022",
      "hitFreq": 17,
      "totalHits": 46,
      "noHitCount": 35,
      "drawsOverdue": 18
    },
    {
      "number": "05",
      "lastHitDate": "09/17/2022",
      "hitFreq": 14,
      "totalHits": 54,
      "noHitCount": 30,
      "drawsOverdue": 16
    },
    {
      "number": "06",
      "lastHitDate": "11/21/2022",
      "hitFreq": 12,
      "totalHits": 63,
      "noHitCount": 3,
      "drawsOverdue": 0
    },
    {
      "number": "07",
      "lastHitDate": "11/19/2022",
      "hitFreq": 14,
      "totalHits": 56,
      "noHitCount": 4,
      "drawsOverdue": 0
    },
    {
      "number": "08",
      "lastHitDate": "10/19/2022",
      "hitFreq": 13,
      "totalHits": 59,
      "noHitCount": 16,
      "drawsOverdue": 3
    },
    {
      "number": "09",
      "lastHitDate": "09/24/2022",
      "hitFreq": 16,
      "totalHits": 49,
      "noHitCount": 27,
      "drawsOverdue": 11
    },
    {
      "number": "10",
      "lastHitDate": "09/28/2022",
      "hitFreq": 12,
      "totalHits": 64,
      "noHitCount": 25,
      "drawsOverdue": 13
    },
    {
      "number": "11",
      "lastHitDate": "11/02/2022",
      "hitFreq": 14,
      "totalHits": 54,
      "noHitCount": 10,
      "drawsOverdue": 0
    },
    {
      "number": "12",
      "lastHitDate": "08/22/2022",
      "hitFreq": 14,
      "totalHits": 57,
      "noHitCount": 41,
      "drawsOverdue": 27
    },
    {
      "number": "13",
      "lastHitDate": "10/31/2022",
      "hitFreq": 17,
      "totalHits": 45,
      "noHitCount": 11,
      "drawsOverdue": 0
    },
    {
      "number": "14",
      "lastHitDate": "11/09/2022",
      "hitFreq": 13,
      "totalHits": 60,
      "noHitCount": 8,
      "drawsOverdue": 0
    },
    {
      "number": "15",
      "lastHitDate": "11/26/2022",
      "hitFreq": 13,
      "totalHits": 60,
      "noHitCount": 1,
      "drawsOverdue": 0
    },
    {
      "number": "16",
      "lastHitDate": "11/12/2022",
      "hitFreq": 13,
      "totalHits": 60,
      "noHitCount": 7,
      "drawsOverdue": 0
    },
    {
      "number": "17",
      "lastHitDate": "10/10/2022",
      "hitFreq": 13,
      "totalHits": 59,
      "noHitCount": 20,
      "drawsOverdue": 7
    },
    {
      "number": "18",
      "lastHitDate": "10/24/2022",
      "hitFreq": 13,
      "totalHits": 58,
      "noHitCount": 14,
      "drawsOverdue": 1
    },
    {
      "number": "19",
      "lastHitDate": "11/14/2022",
      "hitFreq": 14,
      "totalHits": 56,
      "noHitCount": 6,
      "drawsOverdue": 0
    },
    {
      "number": "20",
      "lastHitDate": "11/12/2022",
      "hitFreq": 12,
      "totalHits": 65,
      "noHitCount": 7,
      "drawsOverdue": 0
    },
    {
      "number": "21",
      "lastHitDate": "10/01/2022",
      "hitFreq": 11,
      "totalHits": 73,
      "noHitCount": 24,
      "drawsOverdue": 13
    },
    {
      "number": "22",
      "lastHitDate": "11/02/2022",
      "hitFreq": 13,
      "totalHits": 60,
      "noHitCount": 10,
      "drawsOverdue": 0
    },
    {
      "number": "23",
      "lastHitDate": "10/24/2022",
      "hitFreq": 11,
      "totalHits": 70,
      "noHitCount": 14,
      "drawsOverdue": 3
    },
    {
      "number": "24",
      "lastHitDate": "11/09/2022",
      "hitFreq": 17,
      "totalHits": 47,
      "noHitCount": 8,
      "drawsOverdue": 0
    },
    {
      "number": "25",
      "lastHitDate": "10/22/2022",
      "hitFreq": 15,
      "totalHits": 52,
      "noHitCount": 15,
      "drawsOverdue": 0
    },
    {
      "number": "26",
      "lastHitDate": "10/05/2022",
      "hitFreq": 18,
      "totalHits": 43,
      "noHitCount": 22,
      "drawsOverdue": 4
    },
    {
      "number": "27",
      "lastHitDate": "10/19/2022",
      "hitFreq": 12,
      "totalHits": 65,
      "noHitCount": 16,
      "drawsOverdue": 4
    },
    {
      "number": "28",
      "lastHitDate": "11/19/2022",
      "hitFreq": 12,
      "totalHits": 66,
      "noHitCount": 4,
      "drawsOverdue": 0
    },
    {
      "number": "29",
      "lastHitDate": "11/28/2022",
      "hitFreq": 15,
      "totalHits": 53,
      "noHitCount": 0,
      "drawsOverdue": 0
    },
    {
      "number": "30",
      "lastHitDate": "11/28/2022",
      "hitFreq": 13,
      "totalHits": 58,
      "noHitCount": 0,
      "drawsOverdue": 0
    },
    {
      "number": "31",
      "lastHitDate": "11/23/2022",
      "hitFreq": 15,
      "totalHits": 51,
      "noHitCount": 2,
      "drawsOverdue": 0
    },
    {
      "number": "32",
      "lastHitDate": "11/28/2022",
      "hitFreq": 10,
      "totalHits": 77,
      "noHitCount": 0,
      "drawsOverdue": 0
    },
    {
      "number": "33",
      "lastHitDate": "10/05/2022",
      "hitFreq": 13,
      "totalHits": 62,
      "noHitCount": 22,
      "drawsOverdue": 9
    },
    {
      "number": "34",
      "lastHitDate": "11/16/2022",
      "hitFreq": 17,
      "totalHits": 45,
      "noHitCount": 5,
      "drawsOverdue": 0
    },
    {
      "number": "35",
      "lastHitDate": "11/14/2022",
      "hitFreq": 17,
      "totalHits": 47,
      "noHitCount": 6,
      "drawsOverdue": 0
    },
    {
      "number": "36",
      "lastHitDate": "10/31/2022",
      "hitFreq": 11,
      "totalHits": 70,
      "noHitCount": 11,
      "drawsOverdue": 0
    },
    {
      "number": "37",
      "lastHitDate": "10/26/2022",
      "hitFreq": 12,
      "totalHits": 64,
      "noHitCount": 13,
      "drawsOverdue": 1
    },
    {
      "number": "38",
      "lastHitDate": "09/10/2022",
      "hitFreq": 15,
      "totalHits": 52,
      "noHitCount": 33,
      "drawsOverdue": 18
    },
    {
      "number": "39",
      "lastHitDate": "11/23/2022",
      "hitFreq": 11,
      "totalHits": 68,
      "noHitCount": 2,
      "drawsOverdue": 0
    },
    {
      "number": "40",
      "lastHitDate": "11/21/2022",
      "hitFreq": 13,
      "totalHits": 62,
      "noHitCount": 3,
      "drawsOverdue": 0
    },
    {
      "number": "41",
      "lastHitDate": "10/12/2022",
      "hitFreq": 13,
      "totalHits": 60,
      "noHitCount": 19,
      "drawsOverdue": 6
    },
    {
      "number": "42",
      "lastHitDate": "10/19/2022",
      "hitFreq": 14,
      "totalHits": 57,
      "noHitCount": 16,
      "drawsOverdue": 2
    },
    {
      "number": "43",
      "lastHitDate": "10/08/2022",
      "hitFreq": 16,
      "totalHits": 50,
      "noHitCount": 21,
      "drawsOverdue": 5
    },
    {
      "number": "44",
      "lastHitDate": "11/12/2022",
      "hitFreq": 13,
      "totalHits": 60,
      "noHitCount": 7,
      "drawsOverdue": 0
    },
    {
      "number": "45",
      "lastHitDate": "11/05/2022",
      "hitFreq": 13,
      "totalHits": 58,
      "noHitCount": 9,
      "drawsOverdue": 0
    },
    {
      "number": "46",
      "lastHitDate": "10/29/2022",
      "hitFreq": 17,
      "totalHits": 46,
      "noHitCount": 12,
      "drawsOverdue": 0
    },
    {
      "number": "47",
      "lastHitDate": "11/26/2022",
      "hitFreq": 13,
      "totalHits": 58,
      "noHitCount": 1,
      "drawsOverdue": 0
    },
    {
      "number": "48",
      "lastHitDate": "11/28/2022",
      "hitFreq": 14,
      "totalHits": 54,
      "noHitCount": 0,
      "drawsOverdue": 0
    },
    {
      "number": "49",
      "lastHitDate": "09/03/2022",
      "hitFreq": 17,
      "totalHits": 47,
      "noHitCount": 36,
      "drawsOverdue": 19
    },
    {
      "number": "50",
      "lastHitDate": "11/28/2022",
      "hitFreq": 14,
      "totalHits": 56,
      "noHitCount": 0,
      "drawsOverdue": 0
    },
    {
      "number": "51",
      "lastHitDate": "11/26/2022",
      "hitFreq": 15,
      "totalHits": 52,
      "noHitCount": 1,
      "drawsOverdue": 0
    },
    {
      "number": "52",
      "lastHitDate": "09/14/2022",
      "hitFreq": 13,
      "totalHits": 59,
      "noHitCount": 31,
      "drawsOverdue": 18
    },
    {
      "number": "53",
      "lastHitDate": "11/16/2022",
      "hitFreq": 12,
      "totalHits": 66,
      "noHitCount": 5,
      "drawsOverdue": 0
    },
    {
      "number": "54",
      "lastHitDate": "11/14/2022",
      "hitFreq": 14,
      "totalHits": 55,
      "noHitCount": 6,
      "drawsOverdue": 0
    },
    {
      "number": "55",
      "lastHitDate": "10/22/2022",
      "hitFreq": 14,
      "totalHits": 55,
      "noHitCount": 15,
      "drawsOverdue": 1
    },
    {
      "number": "56",
      "lastHitDate": "11/16/2022",
      "hitFreq": 12,
      "totalHits": 64,
      "noHitCount": 5,
      "drawsOverdue": 0
    },
    {
      "number": "57",
      "lastHitDate": "11/12/2022",
      "hitFreq": 13,
      "totalHits": 59,
      "noHitCount": 7,
      "drawsOverdue": 0
    },
    {
      "number": "58",
      "lastHitDate": "11/12/2022",
      "hitFreq": 15,
      "totalHits": 52,
      "noHitCount": 7,
      "drawsOverdue": 0
    },
    {
      "number": "59",
      "lastHitDate": "10/31/2022",
      "hitFreq": 11,
      "totalHits": 68,
      "noHitCount": 11,
      "drawsOverdue": 0
    },
    {
      "number": "60",
      "lastHitDate": "11/02/2022",
      "hitFreq": 15,
      "totalHits": 52,
      "noHitCount": 10,
      "drawsOverdue": 0
    },
    {
      "number": "61",
      "lastHitDate": "09/17/2022",
      "hitFreq": 10,
      "totalHits": 77,
      "noHitCount": 30,
      "drawsOverdue": 20
    },
    {
      "number": "62",
      "lastHitDate": "11/19/2022",
      "hitFreq": 11,
      "totalHits": 69,
      "noHitCount": 4,
      "drawsOverdue": 0
    },
    {
      "number": "63",
      "lastHitDate": "11/19/2022",
      "hitFreq": 10,
      "totalHits": 74,
      "noHitCount": 4,
      "drawsOverdue": 0
    },
    {
      "number": "64",
      "lastHitDate": "11/19/2022",
      "hitFreq": 12,
      "totalHits": 64,
      "noHitCount": 4,
      "drawsOverdue": 0
    },
    {
      "number": "65",
      "lastHitDate": "10/01/2022",
      "hitFreq": 14,
      "totalHits": 54,
      "noHitCount": 24,
      "drawsOverdue": 10
    },
    {
      "number": "66",
      "lastHitDate": "11/23/2022",
      "hitFreq": 15,
      "totalHits": 52,
      "noHitCount": 2,
      "drawsOverdue": 0
    },
    {
      "number": "67",
      "lastHitDate": "11/21/2022",
      "hitFreq": 13,
      "totalHits": 59,
      "noHitCount": 3,
      "drawsOverdue": 0
    },
    {
      "number": "68",
      "lastHitDate": "10/08/2022",
      "hitFreq": 14,
      "totalHits": 57,
      "noHitCount": 21,
      "drawsOverdue": 7
    },
    {
      "number": "69",
      "lastHitDate": "11/05/2022",
      "hitFreq": 11,
      "totalHits": 72,
      "noHitCount": 9,
      "drawsOverdue": 0
    }
  ]
}